setup.py
mbuild_lib/__init__.py
mbuild_lib-0.0.6.dist-info/METADATA
mbuild_lib-0.0.6.dist-info/WHEEL
mbuild_lib-0.0.6.dist-info/top_level.txt
mbuild_lib-0.0.6.dist-info/RECORD
