Metadata-Version: 2.1
Name: mbuild-lib
Version: 0.0.6
Summary: library for mbuild electronic modules
Home-page: https://makeblock.com
Author: makeblock
Author-email: flashindream@gmail.com
License: UNKNOWN
Platform: UNKNOWN
Requires-Dist: makeblock
